opentrain/__init__.py
opentrain/dataset.py
opentrain/inference.py
opentrain/schemas.py
opentrain/train.py
opentrain/typing.py
opentrain-0.1.0.dist-info/METADATA
opentrain-0.1.0.dist-info/WHEEL
opentrain-0.1.0.dist-info/licenses/LICENSE
opentrain-0.1.0.dist-info/RECORD
